arcas_parser/ContextClasses.py
arcas_parser/__init__.py
arcas_parser/arcas_parser.sh
arcas_parser/cli.py
arcas_parser/launcher.py
arcas_parser/lib_parser.py
arcas_parser/main.py
arcas_parser/monitor.py
arcas_parser/parser.py
arcas_parser/utility.py
arcas_parser-0.2.5.dist-info/METADATA
arcas_parser-0.2.5.dist-info/WHEEL
arcas_parser-0.2.5.dist-info/entry_points.txt
arcas_parser-0.2.5.dist-info/top_level.txt
arcas_parser-0.2.5.dist-info/RECORD
