Metadata-Version: 2.4
Name: arcas_parser
Version: 0.2.5
Summary: Analyzer project for Verilog/OpenCores
Author: Sudheer
Requires-Python: >=3.8
Requires-Dist: pyslang>=8.1.0
